git_bin-0.3.2.dist-info/DESCRIPTION.rst
git_bin-0.3.2.dist-info/METADATA
git_bin-0.3.2.dist-info/RECORD
git_bin-0.3.2.dist-info/WHEEL
git_bin-0.3.2.dist-info/entry_points.txt
git_bin-0.3.2.dist-info/metadata.json
git_bin-0.3.2.dist-info/top_level.txt
gitbin/__init__.py
gitbin/commands.py
gitbin/git.py
gitbin/gitbin.py
gitbin/utils.py
