Metadata-Version: 2.0
Name: git-bin
Version: 0.3.2
Summary: git extension to support binary files
Home-page: https://github.com/cisco-sas/git-bin
Author: srubenst
Author-email: srubenst@cisco.com
License: MIT
Download-URL: https://github.com/cisco-sas/git-bin
Keywords: binary git
Platform: UNKNOWN
Requires-Dist: docopt
Requires-Dist: sh
